PY3021/__init__.py
PY3021/pdf.py
PY3021/tools.py
PY3021-3.3.dist-info/METADATA
PY3021-3.3.dist-info/WHEEL
PY3021-3.3.dist-info/top_level.txt
PY3021-3.3.dist-info/RECORD
